mlos/__init__.py
mlos/module_1.py
mlos/module_2.py
mlos/module_3.py
mlos/module_4.py
mlos/module_5.py
mloscli/__init__.py
mloscli/module_1.py
mloscli/module_2.py
mloscli/module_3.py
mloscli/module_4.py
mloscli/module_5.py
mloscli/module_7.py
mloscli-0.0.1.dist-info/METADATA
mloscli-0.0.1.dist-info/WHEEL
mloscli-0.0.1.dist-info/top_level.txt
mloscli-0.0.1.dist-info/RECORD
